{"results":[{"ProductCodeNAPPI":"626415002","ProductName":"Catheter diagnostic ventricular straig","ProductStrength":"t","ProductForm":"ZZZ"},{"ProductCodeNAPPI":"684766001","ProductName":"Occluder ventricular septal 22mm waist","ProductStrength":"7","ProductForm":"IMP"},{"ProductCodeNAPPI":"126369001","ProductName":"Drainage external ventricular csf moni","ProductStrength":"o","ProductForm":"IMP"},{"ProductCodeNAPPI":"694583001","ProductName":"Device ventricular septal defect occlu","ProductStrength":"i","ProductForm":"IMP"},{"ProductCodeNAPPI":"684790001","ProductName":"Occluder ventricular septal 16mm waist","ProductStrength":"1","ProductForm":"IMP"},{"ProductCodeNAPPI":"656160004","ProductName":"Reservoir csf ventricular side inlet c","ProductStrength":"n","ProductForm":"IMP"},{"ProductCodeNAPPI":"416987001","ProductName":"Catheter csf ventricular 1.2mm x 2.1mm","ProductStrength":"","ProductForm":"ZZZ"},{"ProductCodeNAPPI":"684755001","ProductName":"Occluder ventricular septal 16mm waist","ProductStrength":"7","ProductForm":"IMP"},{"ProductCodeNAPPI":"684777001","ProductName":"Occluder ventricular septal 4mm waist","ProductStrength":".","ProductForm":"IMP"},{"ProductCodeNAPPI":"195408001","ProductName":"Catheter ventricular antibacterial 35c","ProductStrength":"","ProductForm":"IMP"},{"ProductCodeNAPPI":"656419001","ProductName":"Catheter ventricular csf with bioglide","ProductStrength":"2","ProductForm":"ZZZ"},{"ProductCodeNAPPI":"656504001","ProductName":"Catheter ventricular shunt 11mm x 120c","ProductStrength":"","ProductForm":"IMP"},{"ProductCodeNAPPI":"656420001","ProductName":"Catheter ventricular csf with bioglide","ProductStrength":"9","ProductForm":"ZZZ"},{"ProductCodeNAPPI":"656503001","ProductName":"Catheter ventricular shunt 11.5mm x 12","ProductStrength":"c","ProductForm":"IMP"},{"ProductCodeNAPPI":"666556008","ProductName":"Catheter csf ventricular","ProductStrength":"","ProductForm":"IMP"},{"ProductCodeNAPPI":"187075001","ProductName":"Cable rohs glb ventricular 12ft","ProductStrength":"","ProductForm":"ZZZ"},{"ProductCodeNAPPI":"466281001","ProductName":"Catheter translucent ventricular becke","ProductStrength":"","ProductForm":"IMP"},{"ProductCodeNAPPI":"021088001","ProductName":"Device assist ventricular ivac2l pvad","ProductStrength":"0","ProductForm":"ZZZ"},{"ProductCodeNAPPI":"656183006","ProductName":"Shunt ventricular catheter and snap ba","ProductStrength":"e","ProductForm":"IMP"},{"ProductCodeNAPPI":"684781001","ProductName":"Occluder ventricular septal 8mm waist","ProductStrength":".","ProductForm":"IMP"},{"ProductCodeNAPPI":"185448001","ProductName":"Catheter ventricular antibacterial 35c","ProductStrength":"","ProductForm":"IMP"},{"ProductCodeNAPPI":"656161004","ProductName":"Reservoir csf ventricular side inlet c","ProductStrength":"n","ProductForm":"IMP"},{"ProductCodeNAPPI":"276469001","ProductName":"Lead active ventricular 3t mri safe 1","ProductStrength":"","ProductForm":"ZZZ"},{"ProductCodeNAPPI":"684788001","ProductName":"Occluder ventricular septal 14mm waist","ProductStrength":"1","ProductForm":"IMP"},{"ProductCodeNAPPI":"656156008","ProductName":"Catheter csf ventricular standard 1.3m","ProductStrength":"","ProductForm":"IMP"},{"ProductCodeNAPPI":"681903007","ProductName":"Catheter accessory kit ventricular","ProductStrength":"","ProductForm":"IMP"},{"ProductCodeNAPPI":"156921001","ProductName":"Shunt cath ventricular antibacterial p","ProductStrength":"e","ProductForm":"IMP"},{"ProductCodeNAPPI":"656185006","ProductName":"Shunt ventricular catheter and snap ba","ProductStrength":"e","ProductForm":"IMP"},{"ProductCodeNAPPI":"665917001","ProductName":"Lead defibrillation ventricular sprint","ProductStrength":"q","ProductForm":"ZZZ"},{"ProductCodeNAPPI":"626428001","ProductName":"Catheter diagnostic ventricular agled","ProductStrength":"i","ProductForm":"ZZZ"},{"ProductCodeNAPPI":"694582001","ProductName":"Device ventricular septal defect occlu","ProductStrength":"i","ProductForm":"IMP"},{"ProductCodeNAPPI":"196220001","ProductName":"Catheter ventricular drainage 10f","ProductStrength":"","ProductForm":"ZZZ"},{"ProductCodeNAPPI":"196217001","ProductName":"Probe silverline ventricular monitorin","ProductStrength":"","ProductForm":"IMP"},{"ProductCodeNAPPI":"129537001","ProductName":"Pacing lead ventricular navigo 4lv arc","ProductStrength":"8","ProductForm":"ZZZ"},{"ProductCodeNAPPI":"656179006","ProductName":"Shunt ventricular catheter and snap ba","ProductStrength":"e","ProductForm":"IMP"},{"ProductCodeNAPPI":"656182006","ProductName":"Shunt ventricular catheter and snap ba","ProductStrength":"e","ProductForm":"IMP"},{"ProductCodeNAPPI":"463683001","ProductName":"Shunt ventricular reservior 12mm","ProductStrength":"","ProductForm":"IMP"},{"ProductCodeNAPPI":"237955001","ProductName":"Shunt ventricular catheter flushing re","ProductStrength":"e","ProductForm":"IMP"},{"ProductCodeNAPPI":"144834001","ProductName":"Catheter ventricular antimicrobial 23c","ProductStrength":"","ProductForm":"IMP"},{"ProductCodeNAPPI":"684793001","ProductName":"Occluder ventricular septal 18mm waist","ProductStrength":"1","ProductForm":"IMP"},{"ProductCodeNAPPI":"237957001","ProductName":"Shunt ventricular flushing reservoir p","ProductStrength":"e","ProductForm":"IMP"},{"ProductCodeNAPPI":"570500001","ProductName":"Reservior ventricular tr sal - ric sta","ProductStrength":"n","ProductForm":"IMP"},{"ProductCodeNAPPI":"694574001","ProductName":"Device ventricular septal defect occlu","ProductStrength":"i","ProductForm":"IMP"},{"ProductCodeNAPPI":"096040001","ProductName":"Kit icp ventricular cerelink 3.5mm x 1","ProductStrength":"0","ProductForm":"MC3"},{"ProductCodeNAPPI":"174439001","ProductName":"Catheter drainage external ventricular","ProductStrength":"w","ProductForm":"ZZZ"},{"ProductCodeNAPPI":"237949001","ProductName":"Shunt ventricular catheter radiopaque","ProductStrength":"5","ProductForm":"IMP"},{"ProductCodeNAPPI":"243894001","ProductName":"Catheter ventricular pvc closed tip ri","ProductStrength":"h","ProductForm":"ZZZ"},{"ProductCodeNAPPI":"416058001","ProductName":"Shunt pudenz standard ventricular cath","ProductStrength":"t","ProductForm":"IMP"},{"ProductCodeNAPPI":"684785001","ProductName":"Occluder ventricular septal 10mm waist","ProductStrength":"1","ProductForm":"IMP"},{"ProductCodeNAPPI":"656502001","ProductName":"Catheter ventricular shunt 11mm x 90cm","ProductStrength":"","ProductForm":"IMP"},{"ProductCodeNAPPI":"156922001","ProductName":"Shunt cath ventricular antibacterial p","ProductStrength":"e","ProductForm":"IMP"},{"ProductCodeNAPPI":"575445009","ProductName":"Reservoir csf ventricular burr hole co","ProductStrength":"v","ProductForm":"IMP"},{"ProductCodeNAPPI":"129534001","ProductName":"Pacing lead ventricular navigo 4lv 2d","ProductStrength":"8","ProductForm":"ZZZ"},{"ProductCodeNAPPI":"066815001","ProductName":"Catheter ventricular 2 lumen short 20c","ProductStrength":"","ProductForm":"IMP"},{"ProductCodeNAPPI":"156908001","ProductName":"Shunt catheter ventricular antibacteri","ProductStrength":"l","ProductForm":"IMP"},{"ProductCodeNAPPI":"283612001","ProductName":"Stylet ventricular 6057 58cm","ProductStrength":"","ProductForm":"ZZZ"},{"ProductCodeNAPPI":"525237001","ProductName":"Lead bipolar ventricular isoflex optim","ProductStrength":"p","ProductForm":"ZZZ"},{"ProductCodeNAPPI":"595130004","ProductName":"Catheter vent ventricular 2 5.5cm tip","ProductStrength":"e","ProductForm":"ZZZ"},{"ProductCodeNAPPI":"176457001","ProductName":"Catheter ventricular and trocar 2.8mm","ProductStrength":"","ProductForm":"IMP"},{"ProductCodeNAPPI":"066812001","ProductName":"Catheter ventricular 1 lumen tunneling","ProductStrength":"v","ProductForm":"IMP"},{"ProductCodeNAPPI":"175906002","ProductName":"Pack custom atrio ventricular loop sta","ProductStrength":"d","ProductForm":"ZZZ"},{"ProductCodeNAPPI":"697511001","ProductName":"Pacemaker lead ventricular isoflex opt","ProductStrength":"m","ProductForm":"ZZZ"},{"ProductCodeNAPPI":"607432004","ProductName":"Lead cpi fineline 11 ventricular","ProductStrength":"","ProductForm":"ZZZ"},{"ProductCodeNAPPI":"656162004","ProductName":"Reservoir csf ventricular side inlet c","ProductStrength":"n","ProductForm":"IMP"},{"ProductCodeNAPPI":"656501001","ProductName":"Catheter ventricular shunt 8mm x 120cm","ProductStrength":"","ProductForm":"IMP"},{"ProductCodeNAPPI":"237941001","ProductName":"Shunt ventricular catheter with stylet","ProductStrength":"a","ProductForm":"IMP"},{"ProductCodeNAPPI":"493446001","ProductName":"Drainage kit assorted ventricular exte","ProductStrength":"n","ProductForm":"ZZZ"},{"ProductCodeNAPPI":"694581001","ProductName":"Device ventricular septal defect occlu","ProductStrength":"i","ProductForm":"IMP"},{"ProductCodeNAPPI":"595129004","ProductName":"Catheter vent ventricular 1 2.5cm tip","ProductStrength":"e","ProductForm":"ZZZ"},{"ProductCodeNAPPI":"420211001","ProductName":"Shunt pudenz small ventricular cathete","ProductStrength":"s","ProductForm":"IMP"},{"ProductCodeNAPPI":"626455001","ProductName":"Catheter diagnostic ventricular angled","ProductStrength":"p","ProductForm":"ZZZ"},{"ProductCodeNAPPI":"121367001","ProductName":"Cable ventricular long ous mkt","ProductStrength":"","ProductForm":"ZZZ"},{"ProductCodeNAPPI":"463684001","ProductName":"Introducer catheter ventricular quick","ProductStrength":"e","ProductForm":"IMP"},{"ProductCodeNAPPI":"066816001","ProductName":"Catheter ventricular 2 lumen long 30cm","ProductStrength":"9","ProductForm":"IMP"},{"ProductCodeNAPPI":"151374001","ProductName":"Shunt ventricular drainage catheter ex","ProductStrength":"e","ProductForm":"IMP"},{"ProductCodeNAPPI":"129535001","ProductName":"Pacing lead ventricular navigo 4lv 2d","ProductStrength":"8","ProductForm":"ZZZ"},{"ProductCodeNAPPI":"581380002","ProductName":"Pack drainage set ventricular integral","ProductStrength":"","ProductForm":"KIT"},{"ProductCodeNAPPI":"605362001","ProductName":"Lead passive ventricular bipolar durat","ProductStrength":"","ProductForm":"IMP"},{"ProductCodeNAPPI":"111687001","ProductName":"Vent ventricular catheter silicone","ProductStrength":"","ProductForm":"ZZZ"},{"ProductCodeNAPPI":"237944001","ProductName":"Shunt ventricular cath stylet right an","ProductStrength":"l","ProductForm":"IMP"},{"ProductCodeNAPPI":"243891001","ProductName":"Catheter ventricular pvc closed tip ri","ProductStrength":"h","ProductForm":"ZZZ"},{"ProductCodeNAPPI":"684770001","ProductName":"Occluder ventricular septal 24mm waist","ProductStrength":"7","ProductForm":"IMP"},{"ProductCodeNAPPI":"176459001","ProductName":"Catheter ventricular and trocar 3.5mm","ProductStrength":"","ProductForm":"IMP"},{"ProductCodeNAPPI":"185428001","ProductName":"Catheter ventricular antibacterial 20c","ProductStrength":"","ProductForm":"IMP"},{"ProductCodeNAPPI":"126356001","ProductName":"Drainage ventricular catheter radiopaq","ProductStrength":"e","ProductForm":"IMP"},{"ProductCodeNAPPI":"412791001","ProductName":"Pack tubing ventricular assist device","ProductStrength":"a","ProductForm":"ZZZ"},{"ProductCodeNAPPI":"694580001","ProductName":"Device ventricular septal defect occlu","ProductStrength":"i","ProductForm":"IMP"},{"ProductCodeNAPPI":"066814001","ProductName":"Catheter ventricular 1 lumen long 30cm","ProductStrength":"9","ProductForm":"IMP"},{"ProductCodeNAPPI":"226660001","ProductName":"Shunt ventricular with bactiseal","ProductStrength":"","ProductForm":"IMP"},{"ProductCodeNAPPI":"101011001","ProductName":"Lead ventricular screw in quadripolar","ProductStrength":"4","ProductForm":"ZZZ"},{"ProductCodeNAPPI":"626460001","ProductName":"Catheter diagnostic ventricular angled","ProductStrength":"p","ProductForm":"ZZZ"},{"ProductCodeNAPPI":"564637001","ProductName":"Catheter ventricular holter","ProductStrength":"","ProductForm":"IMP"},{"ProductCodeNAPPI":"066813001","ProductName":"Catheter ventricular 1 lumen short 20c","ProductStrength":"","ProductForm":"IMP"},{"ProductCodeNAPPI":"196218001","ProductName":"Catheter silverline ventricular draina","ProductStrength":"e","ProductForm":"ZZZ"},{"ProductCodeNAPPI":"694586001","ProductName":"Device ventricular septal defect occlu","ProductStrength":"i","ProductForm":"IMP"},{"ProductCodeNAPPI":"126366001","ProductName":"Drainage ventricular complete kit csf","ProductStrength":"","ProductForm":"IMP"},{"ProductCodeNAPPI":"684779001","ProductName":"Occluder ventricular septal 6mm waist","ProductStrength":".","ProductForm":"IMP"},{"ProductCodeNAPPI":"276457001","ProductName":"Pacing lead passive ventricular 3t mri","ProductStrength":"s","ProductForm":"ZZZ"},{"ProductCodeNAPPI":"237951001","ProductName":"Shunt ventricular catheter with deflec","ProductStrength":"o","ProductForm":"IMP"},{"ProductCodeNAPPI":"156924001","ProductName":"Shunt cath ventricular antibacterial r","ProductStrength":"g","ProductForm":"IMP"},{"ProductCodeNAPPI":"241671001","ProductName":"Kit microsensor ventricular integrated","ProductStrength":"p","ProductForm":"MC3"},{"ProductCodeNAPPI":"156911001","ProductName":"Shunt catheter ventricular antibacteri","ProductStrength":"l","ProductForm":"IMP"},{"ProductCodeNAPPI":"202900001","ProductName":"Catheter ventricular external drainage","ProductStrength":"s","ProductForm":"ZZZ"},{"ProductCodeNAPPI":"195930001","ProductName":"Ventricular drain edms external monito","ProductStrength":"","ProductForm":"ZZZ"},{"ProductCodeNAPPI":"626418001","ProductName":"Catheter diagnostic ventricular straig","ProductStrength":"t","ProductForm":"ZZZ"},{"ProductCodeNAPPI":"126336001","ProductName":"Monitoring lcp pressio ventricular tun","ProductStrength":"e","ProductForm":"ZZZ"},{"ProductCodeNAPPI":"482054001","ProductName":"Lead attain left ventricular lead 88cm","ProductStrength":"","ProductForm":"ZZZ"},{"ProductCodeNAPPI":"684763001","ProductName":"Occluder ventricular septal 20mm waist","ProductStrength":"7","ProductForm":"IMP"},{"ProductCodeNAPPI":"694566001","ProductName":"Device ventricular septal defect occlu","ProductStrength":"i","ProductForm":"IMP"},{"ProductCodeNAPPI":"656159001","ProductName":"Catheter ventricular trocar bioglide 3","ProductStrength":"c","ProductForm":"IMP"},{"ProductCodeNAPPI":"656155008","ProductName":"Catheter csf ventricular standard 1.3m","ProductStrength":"","ProductForm":"IMP"},{"ProductCodeNAPPI":"129536001","ProductName":"Pacing lead ventricular navigo 4lv arc","ProductStrength":"7","ProductForm":"ZZZ"},{"ProductCodeNAPPI":"156923001","ProductName":"Shunt cath ventricular antibacterial r","ProductStrength":"g","ProductForm":"IMP"},{"ProductCodeNAPPI":"656180006","ProductName":"Shunt ventricular catheter and snap ba","ProductStrength":"e","ProductForm":"IMP"},{"ProductCodeNAPPI":"694579001","ProductName":"Device ventricular septal defect occlu","ProductStrength":"i","ProductForm":"IMP"},{"ProductCodeNAPPI":"176465001","ProductName":"Drain external ventricular and monitor","ProductStrength":"n","ProductForm":"IMP"},{"ProductCodeNAPPI":"463681001","ProductName":"Shunt ventricular port bottom inlet co","ProductStrength":"n","ProductForm":"IMP"},{"ProductCodeNAPPI":"684760001","ProductName":"Occluder ventricular septal 18mm waist","ProductStrength":"7","ProductForm":"IMP"},{"ProductCodeNAPPI":"694578001","ProductName":"Device ventricular septal defect occlu","ProductStrength":"i","ProductForm":"IMP"},{"ProductCodeNAPPI":"684787001","ProductName":"Occluder ventricular septal 12mm waist","ProductStrength":"1","ProductForm":"IMP"},{"ProductCodeNAPPI":"128328001","ProductName":"Shunt ventricular drainage kit","ProductStrength":"","ProductForm":"IMP"},{"ProductCodeNAPPI":"416981001","ProductName":"Reservoir csf ventricular botton inlet","ProductStrength":"c","ProductForm":"IMP"},{"ProductCodeNAPPI":"656158001","ProductName":"Catheter ventricular trocar impregnate","ProductStrength":"","ProductForm":"IMP"},{"ProductCodeNAPPI":"626453001","ProductName":"Catheter diagnostic ventricular angled","ProductStrength":"p","ProductForm":"ZZZ"},{"ProductCodeNAPPI":"694587001","ProductName":"Device ventricular septal defect occlu","ProductStrength":"i","ProductForm":"IMP"},{"ProductCodeNAPPI":"540262006","ProductName":"Cable ventricular patient medtronic","ProductStrength":"","ProductForm":"ZZZ"},{"ProductCodeNAPPI":"237939001","ProductName":"Shunt ventricular catheter with stylet","ProductStrength":"1","ProductForm":"IMP"},{"ProductCodeNAPPI":"656184006","ProductName":"Shunt ventricular catheter and snap ba","ProductStrength":"e","ProductForm":"IMP"},{"ProductCodeNAPPI":"594849004","ProductName":"Pack drain ventricular external withou","ProductStrength":"","ProductForm":"KIT"},{"ProductCodeNAPPI":"107787001","ProductName":"Cardiac ventricular vent catheter pvc","ProductStrength":"6","ProductForm":"ZZZ"},{"ProductCodeNAPPI":"564630001","ProductName":"Catheter ventricular holster","ProductStrength":"","ProductForm":"IMP"},{"ProductCodeNAPPI":"196219001","ProductName":"Catheter silverline ventricular draina","ProductStrength":"e","ProductForm":"ZZZ"},{"ProductCodeNAPPI":"453448001","ProductName":"Reservoir csf ventricular bottom inlet","ProductStrength":"c","ProductForm":"IMP"},{"ProductCodeNAPPI":"175905002","ProductName":"Pack custom atrio ventricular loop sma","ProductStrength":"l","ProductForm":"ZZZ"}]}
